cyberByte/__init__.py
cyberByte/blockChains/__init__.py
cyberByte/blockChains/blockModel.py
cyberByte/blockChains/blockchainModel.py
cyberByte/blockChains/transactionModel.py
cyberByte/clientUI/__init__.py
cyberByte/relayServer/__init__.py
cyberByte-0.0.5.dist-info/LICENSE.txt
cyberByte-0.0.5.dist-info/METADATA
cyberByte-0.0.5.dist-info/WHEEL
cyberByte-0.0.5.dist-info/top_level.txt
cyberByte-0.0.5.dist-info/RECORD
